fubuki/__init__.py
fubuki/app.py
fubuki/controller.py
fubuki/encorder.py
fubuki/exceptions.py
fubuki/openapi.py
fubuki/request.py
fubuki/response.py
fubuki/route.py
fubuki/template.py
fubuki/websocket.py
fubuki/ext/cache/__init__.py
fubuki/ext/cache/deco.py
fubuki/ext/cache/handler.py
fubuki/lib/a2r.py
fubuki/models/asgi.py
fubuki/models/connection.py
fubuki/models/websocket.py
Fubuki-0.2.1.dist-info/LICENSE
Fubuki-0.2.1.dist-info/METADATA
Fubuki-0.2.1.dist-info/WHEEL
Fubuki-0.2.1.dist-info/top_level.txt
Fubuki-0.2.1.dist-info/RECORD
