Metadata-Version: 2.1
Name: Fubuki
Version: 0.2.1
Summary: Next generation hybrid web framework
Author-email: AmaseCocoa <amase.cocoa@gmail.com>
License: MIT
Requires-Python: >=3.10
License-File: LICENSE
Requires-Dist: uvicorn[standard]>=0.30.3
Requires-Dist: pydantic>=2.8.2
Requires-Dist: yarl>=1.9.4
Requires-Dist: asgiref>=3.8.1
Requires-Dist: jinja2>=3.1.4
Requires-Dist: mako>=1.3.5
Requires-Dist: redis>=5.0.7
Requires-Dist: python-multipart>=0.0.9
Provides-Extra: speed
Requires-Dist: orjson>=3.10.6; extra == "speed"
